hw+tests/Register_30b_RTL.v
`ifndef REGISTER_30B_RTL_V
`define REGISTER_30B_RTL_V
`timescale 1ns/1ps // unrelated to actual clock speed of Pynq-Z2, but is specified so that
// we can specify a #0.5 delay
module Register_30b_RTL 
(
  (* keep=1 *) input  logic       clk,
  (* keep=1 *) input  logic [29:0] d,
  (* keep=1 *) output logic [29:0] q
);
    always_ff @(posedge clk) begin
      q <= d;
    end
endmodule
`endif /* REGISTER_30B_RTL_V */

hw+tests/ClockDivider_RTL.v
`ifndef CLOCKDIVIDER_RTL_V
`define CLOCKDIVIDER_RTL_V
`include "Register_30b_RTL.v"
`timescale 1ns/1ps // unrelated to actual clock speed of Pynq-Z2, but is specified so that
// we can specify a #0.5 delay
module ClockDivider_RTL
(
  input logic clk_in,
  input logic [3:0] btn,
  output logic clk_out
);
    localparam STATE_S0 = 30'b011101110011010110010100000000; //0.25Hz (500M cycles)
    // for testing replace 30-bit above with 30'b000000000000000000001000000000 (512 clk_in cycles)
    localparam STATE_S1 = 30'b001110111001101011001010000000; //0.5Hz
    // for testing replace 30-bit above with 30'b000000000000000000000100000000 (256 clk_in cycles)
    localparam STATE_S2 = 30'b000111011100110101100101000000; //1Hz
    // for testing replace 30-bit above with 30'b000000000000000000000010000000 (128 clk_in cycles)
    localparam STATE_S3 = 30'b000011101110011010110010100000; //2Hz
    // for testing replace 30-bit above with 30'b000000000000000000000001000000 (64 clk_in cycles)
    localparam STATE_S4 = 30'b000001110111001101011001010000; //4Hz
    // for testing replace 30-bit above with 30'b000000000000000000000000100000 (32 clk_in cycles)
    localparam STATE_S5 = 30'b000000111011100110101100101000; //8Hz
    // for testing replace 30-bit above with 30'b000000000000000000000000010000 (16 clk_in cycles)
    localparam STATE_S6 = 30'b000000011101110011010110010100; //16Hz
    // for testing replace 30-bit above with 30'b000000000000000000000000001000 (8 clk_in cycles)
    localparam STATE_S7 = 30'b000000001110111001101011001010; //32Hz
    // for testing replace 30-bit above with 30'b000000000000000000000000000100 (4 clk_in cycles)
    localparam STATE_S8 = 30'b000000000111011100110101100101; //64Hz
    // for testing replace 30-bit above with 30'b000000000000000000000000000010 (2 clk_in cycles)
    logic [29:0] state;
    logic [29:0] state_next;
    logic btn3, btn2, btn1, btn0;
    assign btn3 = btn[3];
    assign btn2 = btn[2];
    assign btn1 = btn[1];
    assign btn0 = btn[0];
    Register_30b_RTL state_reg
    (
        .clk(btn3 | btn2 | btn1 | btn0),
        .q (state),
        .d (state_next)
    );
    always_comb begin
        if (btn3) begin
            case (state)
                STATE_S0 : state_next = STATE_S7;
                STATE_S1 : state_next = STATE_S8;
                STATE_S2 : state_next = STATE_S0;
                STATE_S3 : state_next = STATE_S1;
                STATE_S4 : state_next = STATE_S2;
                STATE_S5 : state_next = STATE_S3;
                STATE_S6 : state_next = STATE_S4;
                STATE_S7 : state_next = STATE_S5;
                STATE_S8 : state_next = STATE_S6;
                default : state_next = STATE_S7;
            endcase
        end else begin
            if (btn2) begin
                case (state)
                    STATE_S0 : state_next = STATE_S8;
                    STATE_S1 : state_next = STATE_S0;
                    STATE_S2 : state_next = STATE_S1;
                    STATE_S3 : state_next = STATE_S2;
                    STATE_S4 : state_next = STATE_S3;
                    STATE_S5 : state_next = STATE_S4;
                    STATE_S6 : state_next = STATE_S5;
                    STATE_S7 : state_next = STATE_S6;
                    STATE_S8 : state_next = STATE_S7;
                    default : state_next = STATE_S8;
                endcase
            end else begin
                if (btn1) begin
                    case (state)
                        STATE_S0 : state_next = STATE_S1;
                        STATE_S1 : state_next = STATE_S2;
                        STATE_S2 : state_next = STATE_S3;
                        STATE_S3 : state_next = STATE_S4;
                        STATE_S4 : state_next = STATE_S5;
                        STATE_S5 : state_next = STATE_S6;
                        STATE_S6 : state_next = STATE_S7;
                        STATE_S7 : state_next = STATE_S8;
                        STATE_S8 : state_next = STATE_S0;
                        default : state_next = STATE_S1;
                    endcase
                end else begin
                    if (btn0) begin
                        case (state)
                            STATE_S0 : state_next = STATE_S2;
                            STATE_S1 : state_next = STATE_S3;
                            STATE_S2 : state_next = STATE_S4;
                            STATE_S3 : state_next = STATE_S5;
                            STATE_S4 : state_next = STATE_S6;
                            STATE_S5 : state_next = STATE_S7;
                            STATE_S6 : state_next = STATE_S8;
                            STATE_S7 : state_next = STATE_S0;
                            STATE_S8 : state_next = STATE_S1;
                            default : state_next = STATE_S2;
                        endcase
                    end else begin
                        casez (state)
                            default: state_next = STATE_S0;
                        endcase
                    end
                end
            end
        end
    end
    logic [29:0] counter;
    always_ff @(posedge clk_in) begin
        if (counter < state) begin
            counter <= counter + 30'b000000000000000000000000000001;
            clk_out <= 1'b0;
        end else begin
            counter <= 30'b000000000000000000000000000001;
            clk_out <= 1'b1;  
        end
    end
endmodule
`endif /* CLOCKDIVIDER_RTL_V */

hw+tests/Test_ClockDivider_RTL.v
`include "ClockDivider_RTL.v"
`timescale 1ns/1ps // unrelated to actual clock speed of Pynq-Z2, but is specified so that
// we can specify a #0.5 delay
module Test_ClockDivider_RTL();
    logic dut_clk_in, dut_clk_out;
    logic [3:0] dut_btn;
    ClockDivider_RTL dut
    (
        .clk_in (dut_clk_in),
        .btn (dut_btn),
        .clk_out (dut_clk_out)
    );
    initial begin
        #0.5
        dut_clk_in = 1'b1;
        forever #0.5 dut_clk_in = ~dut_clk_in;
    end

    initial 
        #3694 $finish;

    task check(logic [1:0] mid, logic [3:0] btn1, logic [3:0] btn2, logic [29:0] clock_btn1, logic [29:0] clock_btn2); 
        // code for 1/2 of button 1 clock cycle
        logic [29:0] half_clock_btn1;
        half_clock_btn1[29] = 1'b0;
        half_clock_btn1[28:0] = clock_btn1[29:1];
        //monitors changes in button input and the output clock
        $monitor("time=%3d, %b => %b", $time, dut_btn, dut_clk_out);
        // mid[1] indicates whether a button has been pressed in the middle of a clock cycle or not
        // mid[0] indicates whether the counter is greater than/equal to or less than the clock specified by
        // the second button input
        if (mid == 2'b00) begin
            dut_btn = btn1; 
            #0.5
            // user will not be holding the button, but momentarily pressing it; we will model this
            // period as 0.5 (half of a clk_in cycle) for simplicity's sake
            dut_btn = 4'b0000; 
            #(clock_btn1 - 0.5)
            // first clock cycle = button 1 cycle
            dut_btn = btn2;
            #0.5
            dut_btn = 4'b0000;
            #(clock_btn2 - 0.5);
            // second clock cycle = button 2 cycle
        end else begin
            dut_btn = btn1;
            #0.5
            dut_btn = 4'b0000;
            #(half_clock_btn1 - 0.5)
            // for simplicity's sake, let us say that the user presses the button
            // when exactly half of the clock cycle has passed
            if (mid == 2'b11) begin
                // when the counter is greater than the new clock cycle, the counter resets to 1
                // in the next clk_in rising edge, producing a clk_out rising edge. Then, it 
                // continues with the new clock cycle.
                dut_btn = btn2;
                #0.5
                dut_btn = 4'b0000;
                #0.5
                // first clock cycle = 1/2 button 1 cycle + 1 clk_in cycle
                #(clock_btn2);
                // second clock cycle = button 2 cycle
            end
            if (mid == 2'b10) begin
                // when the counter is less than the new clock cycle, the counter switches to
                // the new clock cycle and produces a clk_out rising edge once the new clock 
                // cycle is finished.
                dut_btn = btn2;
                #0.5
                dut_btn = 4'b0000;
                #(clock_btn2 - half_clock_btn1 - 0.5);
                // total clock cycle = button 2 cycle
            end
            
        end
    endtask
    initial begin
        $dumpfile("Test_ClockDivider_RTL.vcd"); $dumpvars;
        // testing how pressing a button at the middle of a clock cycle will change the clock
        // If mid=10, dut_clk_out should have the button 2 clock cycle
        // If mid=11, dut_clk_out should have a clock cycle of (button 2 clock cycle)+(1 clk_in cycle)
        #0.5 // clk_out = 1 when t = 1 here, since $time is rounded to the nearest whole number
        // for button 3
        check(2'b10, 4'b1000, 4'b1001, 30'b000000000000000000000000000100, 30'b000000000000000000000000010000); //expected cycle = 16 clk_in (clk_out = 1 when t=17)
        check(2'b10, 4'b1010, 4'b1011, 30'b000000000000000000000001000000, 30'b000000000000000000000100000000); // 256 clk_in (t=273)
        check(2'b10, 4'b1100, 4'b1101, 30'b000000000000000000000000000010, 30'b000000000000000000000000001000); // 8 clk_in (t=281)
        check(2'b10, 4'b1110, 4'b1111, 30'b000000000000000000000000100000, 30'b000000000000000000000010000000); // 128 clk_in (t=409)
        check(2'b11, 4'b1000, 4'b1001, 30'b000000000000000000001000000000, 30'b000000000000000000000000000100); // 257 clk_in + 4 clk_in (t=666, 670)
        // for button 2
        check(2'b10, 4'b0100, 4'b0101, 30'b000000000000000000000000001000, 30'b000000000000000000000000010000); // 16 clk_in (t=686)
        check(2'b10, 4'b0110, 4'b0111, 30'b000000000000000000000000100000, 30'b000000000000000000000001000000); // 64 clk_in (t=750)
        check(2'b10, 4'b0100, 4'b0101, 30'b000000000000000000000010000000, 30'b000000000000000000000100000000); // 256 clk_in (t=1006)
        check(2'b11, 4'b0110, 4'b0111, 30'b000000000000000000001000000000, 30'b000000000000000000000000000010); // 257 clk_in + 2 clk_in (t=1263, 1265)
        check(2'b10, 4'b0100, 4'b0101, 30'b000000000000000000000000000100, 30'b000000000000000000000000001000); // 8 clk_in (t=1273)
        // for button 1
        check(2'b11, 4'b0011, 4'b0010, 30'b000000000000000000000000000100, 30'b000000000000000000000000000010); // 3 clk_in + 2 clk_in (t=1276, 1278)
        check(2'b11, 4'b0011, 4'b0010, 30'b000000000000000000001000000000, 30'b000000000000000000000100000000); // 257 clk_in + 256 clk_in (t=1535, 1791)
        check(2'b11, 4'b0011, 4'b0010, 30'b000000000000000000000010000000, 30'b000000000000000000000001000000); // 65 clk_in + 64 clk_in (t=1856, 1920)
        check(2'b11, 4'b0011, 4'b0010, 30'b000000000000000000000000100000, 30'b000000000000000000000000010000); // 17 clk_in + 16 clk_in (t=1937, 1953)
        check(2'b11, 4'b0011, 4'b0010, 30'b000000000000000000000000001000, 30'b000000000000000000000000000100); // 5 clk_in + 4 clk_in (t=1958, 1962)
        // for button 0
        check(2'b11, 4'b0001, 4'b0001, 30'b000000000000000000001000000000, 30'b000000000000000000000010000000); // 257 clk_in + 128 clk_in (t=2219, 2347)
        check(2'b11, 4'b0001, 4'b0001, 30'b000000000000000000000000100000, 30'b000000000000000000000000001000); // 17 clk_in + 8 clk_in (t=2364, 2372)
        check(2'b10, 4'b0001, 4'b0001, 30'b000000000000000000000000000010, 30'b000000000000000000000100000000); // 256 clk_in (t=2628)
        check(2'b11, 4'b0001, 4'b0001, 30'b000000000000000000000001000000, 30'b000000000000000000000000010000); // 33 clk_in + 16 clk_in (t=2661, 2677)
        check(2'b10, 4'b0001, 4'b0001, 30'b000000000000000000000000000100, 30'b000000000000000000001000000000); // 512 clk_in (t=3189)
        // testing how pressing a button at the end of a clock cycle will change the clock
        // dut_clk_out should have the button 1 clock cycle for the first test and the button 2 clock cycle
        // for the second test
        check(2'b00, 4'b0011, 4'b0010, 30'b000000000000000000000100000000, 30'b000000000000000000000010000000); // 256 clk_in + 128 clk_in (t=3445, 3573)
        check(2'b00, 4'b0011, 4'b0010, 30'b000000000000000000000001000000, 30'b000000000000000000000000100000); // 64 clk_in + 32 clk_in (t=3637, 3669)
        check(2'b00, 4'b0011, 4'b0010, 30'b000000000000000000000000010000, 30'b000000000000000000000000001000); // 16 clk_in + 8 clk_in (t=3685, 3693)
    end
endmodule : Test_ClockDivider_RTL

hw+tests/Test_ClockDivider_RTL.vcd
$date
	Thu Oct 17 01:38:26 2024
$end
$version
	Icarus Verilog
$end
$timescale
	1ps
$end
$scope module Test_ClockDivider_RTL $end
$var wire 1 ! dut_clk_out $end
$var reg 4 " dut_btn [3:0] $end
$var reg 1 # dut_clk_in $end
$scope module dut $end
$var wire 4 $ btn [3:0] $end
$var wire 1 # clk_in $end
$var wire 30 % state [29:0] $end
$var wire 1 & btn3 $end
$var wire 1 ' btn2 $end
$var wire 1 ( btn1 $end
$var wire 1 ) btn0 $end
$var parameter 30 * STATE_S0 $end
$var parameter 30 + STATE_S1 $end
$var parameter 30 , STATE_S2 $end
$var parameter 30 - STATE_S3 $end
$var parameter 30 . STATE_S4 $end
$var parameter 30 / STATE_S5 $end
$var parameter 30 0 STATE_S6 $end
$var parameter 30 1 STATE_S7 $end
$var parameter 30 2 STATE_S8 $end
$var reg 1 ! clk_out $end
$var reg 30 3 counter [29:0] $end
$var reg 30 4 state_next [29:0] $end
$scope module state_reg $end
$var wire 1 5 clk $end
$var wire 30 6 d [29:0] $end
$var reg 30 7 q [29:0] $end
$upscope $end
$upscope $end
$scope task check $end
$var reg 4 8 btn1 [3:0] $end
$var reg 4 9 btn2 [3:0] $end
$var reg 30 : clock_btn1 [29:0] $end
$var reg 30 ; clock_btn2 [29:0] $end
$var reg 30 < half_clock_btn1 [29:0] $end
$var reg 2 = mid [1:0] $end
$upscope $end
$upscope $end
$enddefinitions $end
$comment Show the parameter values. $end
$dumpall
b10 2
b100 1
b1000 0
b10000 /
b100000 .
b1000000 -
b10000000 ,
b100000000 +
b1000000000 *
$end
#0
$dumpvars
bx =
bx <
bx ;
bx :
bx 9
bx 8
bx 7
bx 6
x5
bx 4
bx 3
x)
x(
x'
x&
bx %
bx $
x#
bx "
x!
$end
#500
b100 %
b100 7
1!
b1 3
15
b10000 4
b10000 6
1&
0'
0(
0)
b1000 "
b1000 $
b10 <
b10000 ;
b100 :
b1001 9
b1000 8
b10 =
1#
#1000
05
0&
b0 "
b0 $
0#
#1500
0!
b10 3
1#
#2000
0#
#2500
b1000000 4
b1000000 6
b10000 %
b10000 7
b11 3
15
1&
1)
1#
b1001 "
b1001 $
#3000
05
0&
0)
0#
b0 "
b0 $
#3500
b100 3
1#
#4000
0#
#4500
b101 3
1#
#5000
0#
#5500
b110 3
1#
#6000
0#
#6500
b111 3
1#
#7000
0#
#7500
b1000 3
1#
#8000
0#
#8500
b1001 3
1#
#9000
0#
#9500
b1010 3
1#
#10000
0#
#10500
b1011 3
1#
#11000
0#
#11500
b1100 3
1#
#12000
0#
#12500
b1101 3
1#
#13000
0#
#13500
b1110 3
1#
#14000
0#
#14500
b1111 3
1#
#15000
0#
#15500
b10000 3
1#
#16000
0#
#16500
b100000000 4
b100000000 6
b1000000 %
b1000000 7
1!
b1 3
15
1&
1(
1#
b1010 "
b1010 $
b100000 <
b100000000 ;
b1000000 :
b1011 9
b1010 8
#17000
05
0&
0(
0#
b0 "
b0 $
#17500
0!
b10 3
1#
#18000
0#
#18500
b11 3
1#
#19000
0#
#19500
b100 3
1#
#20000
0#
#20500
b101 3
1#
#21000
0#
#21500
b110 3
1#
#22000
0#
#22500
b111 3
1#
#23000
0#
#23500
b1000 3
1#
#24000
0#
#24500
b1001 3
1#
#25000
0#
#25500
b1010 3
1#
#26000
0#
#26500
b1011 3
1#
#27000
0#
#27500
b1100 3
1#
#28000
0#
#28500
b1101 3
1#
#29000
0#
#29500
b1110 3
1#
#30000
0#
#30500
b1111 3
1#
#31000
0#
#31500
b10000 3
1#
#32000
0#
#32500
b10001 3
1#
#33000
0#
#33500
b10010 3
1#
#34000
0#
#34500
b10011 3
1#
#35000
0#
#35500
b10100 3
1#
#36000
0#
#36500
b10101 3
1#
#37000
0#
#37500
b10110 3
1#
#38000
0#
#38500
b10111 3
1#
#39000
0#
#39500
b11000 3
1#
#40000
0#
#40500
b11001 3
1#
#41000
0#
#41500
b11010 3
1#
#42000
0#
#42500
b11011 3
1#
#43000
0#
#43500
b11100 3
1#
#44000
0#
#44500
b11101 3
1#
#45000
0#
#45500
b11110 3
1#
#46000
0#
#46500
b11111 3
1#
#47000
0#
#47500
b100000 3
1#
#48000
0#
#48500
b10 4
b10 6
b100000000 %
b100000000 7
b100001 3
15
1&
1(
1)
1#
b1011 "
b1011 $
#49000
05
0&
0(
0)
0#
b0 "
b0 $
#49500
b100010 3
1#
#50000
0#
#50500
b100011 3
1#
#51000
0#
#51500
b100100 3
1#
#52000
0#
#52500
b100101 3
1#
#53000
0#
#53500
b100110 3
1#
#54000
0#
#54500
b100111 3
1#
#55000
0#
#55500
b101000 3
1#
#56000
0#
#56500
b101001 3
1#
#57000
0#
#57500
b101010 3
1#
#58000
0#
#58500
b101011 3
1#
#59000
0#
#59500
b101100 3
1#
#60000
0#
#60500
b101101 3
1#
#61000
0#
#61500
b101110 3
1#
#62000
0#
#62500
b101111 3
1#
#63000
0#
#63500
b110000 3
1#
#64000
0#
#64500
b110001 3
1#
#65000
0#
#65500
b110010 3
1#
#66000
0#
#66500
b110011 3
1#
#67000
0#
#67500
b110100 3
1#
#68000
0#
#68500
b110101 3
1#
#69000
0#
#69500
b110110 3
1#
#70000
0#
#70500
b110111 3
1#
#71000
0#
#71500
b111000 3
1#
#72000
0#
#72500
b111001 3
1#
#73000
0#
#73500
b111010 3
1#
#74000
0#
#74500
b111011 3
1#
#75000
0#
#75500
b111100 3
1#
#76000
0#
#76500
b111101 3
1#
#77000
0#
#77500
b111110 3
1#
#78000
0#
#78500
b111111 3
1#
#79000
0#
#79500
b1000000 3
1#
#80000
0#
#80500
b1000001 3
1#
#81000
0#
#81500
b1000010 3
1#
#82000
0#
#82500
b1000011 3
1#
#83000
0#
#83500
b1000100 3
1#
#84000
0#
#84500
b1000101 3
1#
#85000
0#
#85500
b1000110 3
1#
#86000
0#
#86500
b1000111 3
1#
#87000
0#
#87500
b1001000 3
1#
#88000
0#
#88500
b1001001 3
1#
#89000
0#
#89500
b1001010 3
1#
#90000
0#
#90500
b1001011 3
1#
#91000
0#
#91500
b1001100 3
1#
#92000
0#
#92500
b1001101 3
1#
#93000
0#
#93500
b1001110 3
1#
#94000
0#
#94500
b1001111 3
1#
#95000
0#
#95500
b1010000 3
1#
#96000
0#
#96500
b1010001 3
1#
#97000
0#
#97500
b1010010 3
1#
#98000
0#
#98500
b1010011 3
1#
#99000
0#
#99500
b1010100 3
1#
#100000
0#
#100500
b1010101 3
1#
#101000
0#
#101500
b1010110 3
1#
#102000
0#
#102500
b1010111 3
1#
#103000
0#
#103500
b1011000 3
1#
#104000
0#
#104500
b1011001 3
1#
#105000
0#
#105500
b1011010 3
1#
#106000
0#
#106500
b1011011 3
1#
#107000
0#
#107500
b1011100 3
1#
#108000
0#
#108500
b1011101 3
1#
#109000
0#
#109500
b1011110 3
1#
#110000
0#
#110500
b1011111 3
1#
#111000
0#
#111500
b1100000 3
1#
#112000
0#
#112500
b1100001 3
1#
#113000
0#
#113500
b1100010 3
1#
#114000
0#
#114500
b1100011 3
1#
#115000
0#
#115500
b1100100 3
1#
#116000
0#
#116500
b1100101 3
1#
#117000
0#
#117500
b1100110 3
1#
#118000
0#
#118500
b1100111 3
1#
#119000
0#
#119500
b1101000 3
1#
#120000
0#
#120500
b1101001 3
1#
#121000
0#
#121500
b1101010 3
1#
#122000
0#
#122500
b1101011 3
1#
#123000
0#
#123500
b1101100 3
1#
#124000
0#
#124500
b1101101 3
1#
#125000
0#
#125500
b1101110 3
1#
#126000
0#
#126500
b1101111 3
1#
#127000
0#
#127500
b1110000 3
1#
#128000
0#
#128500
b1110001 3
1#
#129000
0#
#129500
b1110010 3
1#
#130000
0#
#130500
b1110011 3
1#
#131000
0#
#131500
b1110100 3
1#
#132000
0#
#132500
b1110101 3
1#
#133000
0#
#133500
b1110110 3
1#
#134000
0#
#134500
b1110111 3
1#
#135000
0#
#135500
b1111000 3
1#
#136000
0#
#136500
b1111001 3
1#
#137000
0#
#137500
b1111010 3
1#
#138000
0#
#138500
b1111011 3
1#
#139000
0#
#139500
b1111100 3
1#
#140000
0#
#140500
b1111101 3
1#
#141000
0#
#141500
b1111110 3
1#
#142000
0#
#142500
b1111111 3
1#
#143000
0#
#143500
b10000000 3
1#
#144000
0#
#144500
b10000001 3
1#
#145000
0#
#145500
b10000010 3
1#
#146000
0#
#146500
b10000011 3
1#
#147000
0#
#147500
b10000100 3
1#
#148000
0#
#148500
b10000101 3
1#
#149000
0#
#149500
b10000110 3
1#
#150000
0#
#150500
b10000111 3
1#
#151000
0#
#151500
b10001000 3
1#
#152000
0#
#152500
b10001001 3
1#
#153000
0#
#153500
b10001010 3
1#
#154000
0#
#154500
b10001011 3
1#
#155000
0#
#155500
b10001100 3
1#
#156000
0#
#156500
b10001101 3
1#
#157000
0#
#157500
b10001110 3
1#
#158000
0#
#158500
b10001111 3
1#
#159000
0#
#159500
b10010000 3
1#
#160000
0#
#160500
b10010001 3
1#
#161000
0#
#161500
b10010010 3
1#
#162000
0#
#162500
b10010011 3
1#
#163000
0#
#163500
b10010100 3
1#
#164000
0#
#164500
b10010101 3
1#
#165000
0#
#165500
b10010110 3
1#
#166000
0#
#166500
b10010111 3
1#
#167000
0#
#167500
b10011000 3
1#
#168000
0#
#168500
b10011001 3
1#
#169000
0#
#169500
b10011010 3
1#
#170000
0#
#170500
b10011011 3
1#
#171000
0#
#171500
b10011100 3
1#
#172000
0#
#172500
b10011101 3
1#
#173000
0#
#173500
b10011110 3
1#
#174000
0#
#174500
b10011111 3
1#
#175000
0#
#175500
b10100000 3
1#
#176000
0#
#176500
b10100001 3
1#
#177000
0#
#177500
b10100010 3
1#
#178000
0#
#178500
b10100011 3
1#
#179000
0#
#179500
b10100100 3
1#
#180000
0#
#180500
b10100101 3
1#
#181000
0#
#181500
b10100110 3
1#
#182000
0#
#182500
b10100111 3
1#
#183000
0#
#183500
b10101000 3
1#
#184000
0#
#184500
b10101001 3
1#
#185000
0#
#185500
b10101010 3
1#
#186000
0#
#186500
b10101011 3
1#
#187000
0#
#187500
b10101100 3
1#
#188000
0#
#188500
b10101101 3
1#
#189000
0#
#189500
b10101110 3
1#
#190000
0#
#190500
b10101111 3
1#
#191000
0#
#191500
b10110000 3
1#
#192000
0#
#192500
b10110001 3
1#
#193000
0#
#193500
b10110010 3
1#
#194000
0#
#194500
b10110011 3
1#
#195000
0#
#195500
b10110100 3
1#
#196000
0#
#196500
b10110101 3
1#
#197000
0#
#197500
b10110110 3
1#
#198000
0#
#198500
b10110111 3
1#
#199000
0#
#199500
b10111000 3
1#
#200000
0#
#200500
b10111001 3
1#
#201000
0#
#201500
b10111010 3
1#
#202000
0#
#202500
b10111011 3
1#
#203000
0#
#203500
b10111100 3
1#
#204000
0#
#204500
b10111101 3
1#
#205000
0#
#205500
b10111110 3
1#
#206000
0#
#206500
b10111111 3
1#
#207000
0#
#207500
b11000000 3
1#
#208000
0#
#208500
b11000001 3
1#
#209000
0#
#209500
b11000010 3
1#
#210000
0#
#210500
b11000011 3
1#
#211000
0#
#211500
b11000100 3
1#
#212000
0#
#212500
b11000101 3
1#
#213000
0#
#213500
b11000110 3
1#
#214000
0#
#214500
b11000111 3
1#
#215000
0#
#215500
b11001000 3
1#
#216000
0#
#216500
b11001001 3
1#
#217000
0#
#217500
b11001010 3
1#
#218000
0#
#218500
b11001011 3
1#
#219000
0#
#219500
b11001100 3
1#
#220000
0#
#220500
b11001101 3
1#
#221000
0#
#221500
b11001110 3
1#
#222000
0#
#222500
b11001111 3
1#
#223000
0#
#223500
b11010000 3
1#
#224000
0#
#224500
b11010001 3
1#
#225000
0#
#225500
b11010010 3
1#
#226000
0#
#226500
b11010011 3
1#
#227000
0#
#227500
b11010100 3
1#
#228000
0#
#228500
b11010101 3
1#
#229000
0#
#229500
b11010110 3
1#
#230000
0#
#230500
b11010111 3
1#
#231000
0#
#231500
b11011000 3
1#
#232000
0#
#232500
b11011001 3
1#
#233000
0#
#233500
b11011010 3
1#
#234000
0#
#234500
b11011011 3
1#
#235000
0#
#235500
b11011100 3
1#
#236000
0#
#236500
b11011101 3
1#
#237000
0#
#237500
b11011110 3
1#
#238000
0#
#238500
b11011111 3
1#
#239000
0#
#239500
b11100000 3
1#
#240000
0#
#240500
b11100001 3
1#
#241000
0#
#241500
b11100010 3
1#
#242000
0#
#242500
b11100011 3
1#
#243000
0#
#243500
b11100100 3
1#
#244000
0#
#244500
b11100101 3
1#
#245000
0#
#245500
b11100110 3
1#
#246000
0#
#246500
b11100111 3
1#
#247000
0#
#247500
b11101000 3
1#
#248000
0#
#248500
b11101001 3
1#
#249000
0#
#249500
b11101010 3
1#
#250000
0#
#250500
b11101011 3
1#
#251000
0#
#251500
b11101100 3
1#
#252000
0#
#252500
b11101101 3
1#
#253000
0#
#253500
b11101110 3
1#
#254000
0#
#254500
b11101111 3
1#
#255000
0#
#255500
b11110000 3
1#
#256000
0#
#256500
b11110001 3
1#
#257000
0#
#257500
b11110010 3
1#
#258000
0#
#258500
b11110011 3
1#
#259000
0#
#259500
b11110100 3
1#
#260000
0#
#260500
b11110101 3
1#
#261000
0#
#261500
b11110110 3
1#
#262000
0#
#262500
b11110111 3
1#
#263000
0#
#263500
b11111000 3
1#
#264000
0#
#264500
b11111001 3
1#
#265000
0#
#265500
b11111010 3
1#
#266000
0#
#266500
b11111011 3
1#
#267000
0#
#267500
b11111100 3
1#
#268000
0#
#268500
b11111101 3
1#
#269000
0#
#269500
b11111110 3
1#
#270000
0#
#270500
b11111111 3
1#
#271000
0#
#271500
b100000000 3
1#
#272000
0#
#272500
b1000 4
b1000 6
b10 %
b10 7
1!
b1 3
15
1&
1'
1#
b1100 "
b1100 $
b1 <
b1000 ;
b10 :
b1101 9
b1100 8
#273000
05
0&
0'
0#
b0 "
b0 $
#273500
b100000 4
b100000 6
b1000 %
b1000 7
0!
b10 3
15
1&
1'
1)
1#
b1101 "
b1101 $
#274000
05
0&
0'
0)
0#
b0 "
b0 $
#274500
b11 3
1#
#275000
0#
#275500
b100 3
1#
#276000
0#
#276500
b101 3
1#
#277000
0#
#277500
b110 3
1#
#278000
0#
#278500
b111 3
1#
#279000
0#
#279500
b1000 3
1#
#280000
0#
#280500
b10000000 4
b10000000 6
b100000 %
b100000 7
1!
b1 3
15
1&
1'
1(
1#
b1110 "
b1110 $
b10000 <
b10000000 ;
b100000 :
b1111 9
b1110 8
#281000
05
0&
0'
0(
0#
b0 "
b0 $
#281500
0!
b10 3
1#
#282000
0#
#282500
b11 3
1#
#283000
0#
#283500
b100 3
1#
#284000
0#
#284500
b101 3
1#
#285000
0#
#285500
b110 3
1#
#286000
0#
#286500
b111 3
1#
#287000
0#
#287500
b1000 3
1#
#288000
0#
#288500
b1001 3
1#
#289000
0#
#289500
b1010 3
1#
#290000
0#
#290500
b1011 3
1#
#291000
0#
#291500
b1100 3
1#
#292000
0#
#292500
b1101 3
1#
#293000
0#
#293500
b1110 3
1#
#294000
0#
#294500
b1111 3
1#
#295000
0#
#295500
b10000 3
1#
#296000
0#
#296500
b1000000000 4
b1000000000 6
b10000000 %
b10000000 7
b10001 3
15
1&
1'
1(
1)
1#
b1111 "
b1111 $
#297000
05
0&
0'
0(
0)
0#
b0 "
b0 $
#297500
b10010 3
1#
#298000
0#
#298500
b10011 3
1#
#299000
0#
#299500
b10100 3
1#
#300000
0#
#300500
b10101 3
1#
#301000
0#
#301500
b10110 3
1#
#302000
0#
#302500
b10111 3
1#
#303000
0#
#303500
b11000 3
1#
#304000
0#
#304500
b11001 3
1#
#305000
0#
#305500
b11010 3
1#
#306000
0#
#306500
b11011 3
1#
#307000
0#
#307500
b11100 3
1#
#308000
0#
#308500
b11101 3
1#
#309000
0#
#309500
b11110 3
1#
#310000
0#
#310500
b11111 3
1#
#311000
0#
#311500
b100000 3
1#
#312000
0#
#312500
b100001 3
1#
#313000
0#
#313500
b100010 3
1#
#314000
0#
#314500
b100011 3
1#
#315000
0#
#315500
b100100 3
1#
#316000
0#
#316500
b100101 3
1#
#317000
0#
#317500
b100110 3
1#
#318000
0#
#318500
b100111 3
1#
#319000
0#
#319500
b101000 3
1#
#320000
0#
#320500
b101001 3
1#
#321000
0#
#321500
b101010 3
1#
#322000
0#
#322500
b101011 3
1#
#323000
0#
#323500
b101100 3
1#
#324000
0#
#324500
b101101 3
1#
#325000
0#
#325500
b101110 3
1#
#326000
0#
#326500
b101111 3
1#
#327000
0#
#327500
b110000 3
1#
#328000
0#
#328500
b110001 3
1#
#329000
0#
#329500
b110010 3
1#
#330000
0#
#330500
b110011 3
1#
#331000
0#
#331500
b110100 3
1#
#332000
0#
#332500
b110101 3
1#
#333000
0#
#333500
b110110 3
1#
#334000
0#
#334500
b110111 3
1#
#335000
0#
#335500
b111000 3
1#
#336000
0#
#336500
b111001 3
1#
#337000
0#
#337500
b111010 3
1#
#338000
0#
#338500
b111011 3
1#
#339000
0#
#339500
b111100 3
1#
#340000
0#
#340500
b111101 3
1#
#341000
0#
#341500
b111110 3
1#
#342000
0#
#342500
b111111 3
1#
#343000
0#
#343500
b1000000 3
1#
#344000
0#
#344500
b1000001 3
1#
#345000
0#
#345500
b1000010 3
1#
#346000
0#
#346500
b1000011 3
1#
#347000
0#
#347500
b1000100 3
1#
#348000
0#
#348500
b1000101 3
1#
#349000
0#
#349500
b1000110 3
1#
#350000
0#
#350500
b1000111 3
1#
#351000
0#
#351500
b1001000 3
1#
#352000
0#
#352500
b1001001 3
1#
#353000
0#
#353500
b1001010 3
1#
#354000
0#
#354500
b1001011 3
1#
#355000
0#
#355500
b1001100 3
1#
#356000
0#
#356500
b1001101 3
1#
#357000
0#
#357500
b1001110 3
1#
#358000
0#
#358500
b1001111 3
1#
#359000
0#
#359500
b1010000 3
1#
#360000
0#
#360500
b1010001 3
1#
#361000
0#
#361500
b1010010 3
1#
#362000
0#
#362500
b1010011 3
1#
#363000
0#
#363500
b1010100 3
1#
#364000
0#
#364500
b1010101 3
1#
#365000
0#
#365500
b1010110 3
1#
#366000
0#
#366500
b1010111 3
1#
#367000
0#
#367500
b1011000 3
1#
#368000
0#
#368500
b1011001 3
1#
#369000
0#
#369500
b1011010 3
1#
#370000
0#
#370500
b1011011 3
1#
#371000
0#
#371500
b1011100 3
1#
#372000
0#
#372500
b1011101 3
1#
#373000
0#
#373500
b1011110 3
1#
#374000
0#
#374500
b1011111 3
1#
#375000
0#
#375500
b1100000 3
1#
#376000
0#
#376500
b1100001 3
1#
